{
	"tags": [
		{
			"id": "tag1",
			"name": "Development",
			"color": "#3B82F6"
		},
		{
			"id": "tag2",
			"name": "Design",
			"color": "#10B981"
		},
		{
			"id": "tag3",
			"name": "Testing",
			"color": "#F59E0B"
		},
		{
			"id": "tag4",
			"name": "Review",
			"color": "#8B5CF6"
		},
		{
			"id": "tag5",
			"name": "Release",
			"color": "#EF4444"
		}
	],
	"tasks": [
		{
			"id": "task1",
			"name": "Frontend Development",
			"periods": [
				{
					"id": "period1",
					"startDate": "2025-01-10",
					"endDate": "2025-01-15",
					"note": "UI Implementation",
					"tagId": "tag1"
				},
				{
					"id": "period2",
					"startDate": "2025-01-20",
					"endDate": "2025-01-22",
					"note": "API Integration",
					"tagId": "tag1"
				}
			]
		},
		{
			"id": "task2",
			"name": "Backend Development",
			"periods": [
				{
					"id": "period3",
					"startDate": "2025-01-08",
					"endDate": "2025-01-12",
					"note": "Database Design",
					"tagId": "tag2"
				}
			]
		},
		{
			"id": "task3",
			"name": "Mobile App",
			"periods": []
		}
	]
}
